README.rst
setup.cfg
setup.py
camisole/__init__.py
camisole/__main__.py
camisole/http.py
camisole/isolate.py
camisole/loader.py
camisole/models.py
camisole/ref.py
camisole/schema.py
camisole/system.py
camisole/utils.py
camisole.egg-info/PKG-INFO
camisole.egg-info/SOURCES.txt
camisole.egg-info/dependency_links.txt
camisole.egg-info/entry_points.txt
camisole.egg-info/requires.txt
camisole.egg-info/top_level.txt
camisole/languages/__init__.py
camisole/languages/ada.py
camisole/languages/brainfuck.py
camisole/languages/c.py
camisole/languages/csharp.py
camisole/languages/cxx.py
camisole/languages/fsharp.py
camisole/languages/haskell.py
camisole/languages/java.py
camisole/languages/javascript.py
camisole/languages/lua.py
camisole/languages/ocaml.py
camisole/languages/pascal.py
camisole/languages/perl.py
camisole/languages/php.py
camisole/languages/python.py
camisole/languages/ruby.py
camisole/languages/rust.py
camisole/languages/scheme.py
camisole/languages/visualbasic.py