Metadata-Version: 1.0
Name: camisole
Version: 0.5
Summary: An asyncio-based source compiler and test runner.
Home-page: https://github.com/prologin/camisole
Author: Antoine Pietri, Alexandre Macabies
Author-email: UNKNOWN
License: GPL
Platform: UNKNOWN
